wordloom/__about__.py
wordloom/__init__.py
wordloom/wordloom.py
wordloom/resources/wordloom/sample.toml
wordloom-0.10.0.dist-info/METADATA
wordloom-0.10.0.dist-info/WHEEL
wordloom-0.10.0.dist-info/licenses/LICENSE
wordloom-0.10.0.dist-info/licenses/LICENSE-spec
wordloom-0.10.0.dist-info/RECORD
