Metadata-Version: 2.4
Name: wordloom
Version: 0.10.0
Summary: Convention for expressing language text and templates for AI language model-related uses, for example prompt templates. The format is based on TOML, and word looms are meant to be kept in resource directories for use with code invoking LLMs.
Project-URL: Documentation, https://github.com/OoriData/WordLoom#readme
Project-URL: Issues, https://github.com/OoriData/WordLoom/issues
Project-URL: Source, https://github.com/OoriData/WordLoom
Author-email: Uche Ogbuji <uche@ogbuji.net>
License-Expression: Apache-2.0
License-File: LICENSE
License-File: LICENSE-spec
Keywords: i18n,llm,localization,prompt,template,toml
Classifier: Development Status :: 4 - Beta
Classifier: Programming Language :: Python
Classifier: Programming Language :: Python :: 3.12
Classifier: Programming Language :: Python :: 3.13
Classifier: Programming Language :: Python :: Implementation :: CPython
Classifier: Programming Language :: Python :: Implementation :: PyPy
Requires-Python: >=3.12
Requires-Dist: tomli
Provides-Extra: dev
Requires-Dist: build; extra == 'dev'
Requires-Dist: hatch; extra == 'dev'
Requires-Dist: pipdeptree; extra == 'dev'
Requires-Dist: pytest; extra == 'dev'
Requires-Dist: pytest-mock; extra == 'dev'
Requires-Dist: ruff; extra == 'dev'
Requires-Dist: twine; extra == 'dev'
